{
  "timestamp": 1755481594.4612727,
  "overall_status": "EXCELLENT",
  "gates": {
    "Code Structure": {
      "score": 100,
      "max_score": 100,
      "percentage": 100.0,
      "status": "PASS",
      "details": {
        "directory_structure": {
          "required": [
            "src",
            "src/models",
            "src/algorithms",
            "src/utils",
            "src/optimization",
            "src/monitoring",
            "src/security",
            "tests",
            "examples",
            "benchmarks"
          ],
          "existing": [
            "src",
            "src/models",
            "src/algorithms",
            "src/utils",
            "src/optimization",
            "src/monitoring",
            "src/security",
            "tests",
            "examples",
            "benchmarks"
          ],
          "score": 50
        },
        "key_files": {
          "required": [
            "README.md",
            "setup.py",
            "requirements.txt",
            "src/__init__.py",
            "src/models/__init__.py",
            "examples/neuromorphic_demo.py"
          ],
          "existing": [
            "README.md",
            "setup.py",
            "requirements.txt",
            "src/__init__.py",
            "src/models/__init__.py",
            "examples/neuromorphic_demo.py"
          ],
          "score": 30
        },
        "code_metrics": {
          "total_python_files": 71,
          "lines_of_code": 22831,
          "has_docstrings": true
        }
      }
    },
    "Functionality": {
      "score": 100,
      "max_score": 100,
      "percentage": 100.0,
      "status": "PASS",
      "details": {
        "demo_tests": {
          "total": 3,
          "working": [
            "Neuromorphic Demo",
            "Health Monitoring",
            "Performance Optimization"
          ],
          "score": 60
        },
        "model_implementations": {
          "required": [
            "src/models/lif_neuron.py",
            "src/models/spiking_neural_network.py",
            "src/models/liquid_state_machine.py"
          ],
          "existing": [
            "src/models/lif_neuron.py",
            "src/models/spiking_neural_network.py",
            "src/models/liquid_state_machine.py"
          ],
          "score": 30
        },
        "algorithms": {
          "count": 7,
          "files": [
            "__init__.py",
            "event_processor.py",
            "event_processor_fixed.py",
            "novel_stdp.py",
            "plasticity.py",
            "spike_processor.py",
            "temporal_coding.py"
          ]
        }
      }
    },
    "Performance": {
      "score": 100,
      "max_score": 100,
      "percentage": 100.0,
      "status": "PASS",
      "details": {
        "optimization_features": {
          "total": 4,
          "implemented": [
            "Caching",
            "Performance Optimizer",
            "Memory Optimizer",
            "Concurrent Processor"
          ],
          "score": 60
        },
        "performance_demo": {
          "working": true,
          "has_metrics": true
        }
      }
    },
    "Security": {
      "score": 60,
      "max_score": 100,
      "percentage": 60.0,
      "status": "FAIL",
      "details": {
        "security_features": {
          "total": 3,
          "implemented": [
            "Input Validator",
            "Security Manager",
            "Error Handling"
          ],
          "score": 60
        },
        "security_practices": {
          "files_with_security_indicators": 3,
          "score": 0
        },
        "security_scan": {
          "issues_found": 1,
          "clean": false
        }
      }
    },
    "Documentation": {
      "score": 100,
      "max_score": 100,
      "percentage": 100.0,
      "status": "PASS",
      "details": {
        "documentation_files": {
          "total": 5,
          "existing": [
            "README",
            "API Reference",
            "Changelog",
            "Contributing",
            "Deployment Guide"
          ],
          "score": 75
        },
        "readme_quality": {
          "length": 3622,
          "has_installation": false,
          "has_usage": true,
          "has_examples": true,
          "score": 15
        }
      }
    },
    "Dependencies": {
      "score": 90,
      "max_score": 100,
      "percentage": 90.0,
      "status": "PASS",
      "details": {
        "dependency_files": {
          "existing": [
            "requirements.txt",
            "setup.py"
          ],
          "score": 50
        },
        "requirements_analysis": {
          "total_deps": 19,
          "pinned_deps": 19,
          "pinning_ratio": 1.0
        }
      }
    },
    "Examples": {
      "score": 75,
      "max_score": 100,
      "percentage": 75.0,
      "status": "FAIL",
      "details": {
        "example_files": {
          "count": 6,
          "files": [
            "__init__.py",
            "basic_spiking_network.py",
            "liquid_state_machine_demo.py",
            "health_monitoring_demo.py",
            "neuromorphic_demo.py",
            "performance_optimization_demo.py"
          ]
        },
        "key_examples": {
          "total": 3,
          "working": [
            "neuromorphic_demo.py",
            "health_monitoring_demo.py",
            "performance_optimization_demo.py"
          ],
          "score": 45
        },
        "notebooks": {
          "count": 0,
          "files": []
        }
      }
    },
    "Deployment": {
      "score": 70,
      "max_score": 100,
      "percentage": 70.0,
      "status": "FAIL",
      "details": {
        "deployment_files": {
          "total": 4,
          "existing": [
            "Deployment Config",
            "Deployment Guide"
          ]
        },
        "deployment_directory": {
          "exists": true,
          "file_count": 2,
          "files": [
            "deployment-config.yaml",
            "production_deployment.py"
          ]
        },
        "configuration": {
          "config_files": 2,
          "files": [
            "deployment_config.json",
            "deployment_config_dev.json"
          ]
        }
      }
    }
  },
  "summary": {
    "total_score": 695,
    "max_score": 800,
    "percentage": 86.875,
    "passed_gates": 5,
    "failed_gates": 3,
    "total_gates": 8
  },
  "recommendations": [
    "Implement comprehensive input validation and security measures",
    "Add more working examples and fix syntax errors",
    "Add deployment configurations and containerization",
    "Excellent work! Consider advanced features and optimizations"
  ]
}